quantrocket/__init__.py
quantrocket/_version.py
quantrocket/account.py
quantrocket/blotter.py
quantrocket/codeload.py
quantrocket/countdown.py
quantrocket/db.py
quantrocket/exceptions.py
quantrocket/flightlog.py
quantrocket/fundamental.py
quantrocket/history.py
quantrocket/houston.py
quantrocket/ibg.py
quantrocket/license.py
quantrocket/master.py
quantrocket/moonshot.py
quantrocket/price.py
quantrocket/py.typed
quantrocket/realtime.py
quantrocket/satellite.py
quantrocket/version.py
quantrocket/zipline.py
quantrocket/_cli/__init__.py
quantrocket/_cli/commands.py
quantrocket/_cli/subcommands/__init__.py
quantrocket/_cli/subcommands/account.py
quantrocket/_cli/subcommands/blotter.py
quantrocket/_cli/subcommands/codeload.py
quantrocket/_cli/subcommands/countdown.py
quantrocket/_cli/subcommands/db.py
quantrocket/_cli/subcommands/flightlog.py
quantrocket/_cli/subcommands/fundamental.py
quantrocket/_cli/subcommands/history.py
quantrocket/_cli/subcommands/houston.py
quantrocket/_cli/subcommands/ibg.py
quantrocket/_cli/subcommands/license.py
quantrocket/_cli/subcommands/master.py
quantrocket/_cli/subcommands/moonshot.py
quantrocket/_cli/subcommands/realtime.py
quantrocket/_cli/subcommands/satellite.py
quantrocket/_cli/subcommands/version.py
quantrocket/_cli/subcommands/zipline.py
quantrocket/_cli/utils/__init__.py
quantrocket/_cli/utils/files.py
quantrocket/_cli/utils/output.py
quantrocket/_cli/utils/parse.py
quantrocket/_cli/utils/stream.py
quantrocket/_cli/utils/completers/__init__.py
quantrocket/_cli/utils/completers/countries.py
quantrocket/_cli/utils/completers/currencies.py
quantrocket/_tests/__init__.py
quantrocket/_tests/test_blotter.py
quantrocket/_tests/test_fundamental.py
quantrocket/_tests/test_master.py
quantrocket/_tests/test_moonshot.py
quantrocket/_tests/test_price.py
quantrocket/_tests/test_utils.py
quantrocket/utils/__init__.py
quantrocket/utils/_parse.py
quantrocket/utils/_typing.py
quantrocket/utils/_warn.py
quantrocket/utils/dt.py
quantrocket_client-2.11.0.0.dist-info/LICENSE.txt
quantrocket_client-2.11.0.0.dist-info/METADATA
quantrocket_client-2.11.0.0.dist-info/WHEEL
quantrocket_client-2.11.0.0.dist-info/entry_points.txt
quantrocket_client-2.11.0.0.dist-info/top_level.txt
quantrocket_client-2.11.0.0.dist-info/RECORD
